safeeval/__init__.py
tests/__init__.py
tests/simpletests.py
safeeval-0.0.5.dist-info/LICENSE
safeeval-0.0.5.dist-info/METADATA
safeeval-0.0.5.dist-info/WHEEL
safeeval-0.0.5.dist-info/top_level.txt
safeeval-0.0.5.dist-info/RECORD
