Metadata-Version: 2.1
Name: safeeval
Version: 0.0.5
Summary: Safely evaluates simple python expressions
Home-page: https://github.com/viur-framework/safeeval
Author: Mausbrand Informationssysteme GmbH
Author-email: team@viur.dev
License: UNKNOWN
Platform: UNKNOWN
Classifier: Programming Language :: Python :: 3
Classifier: License :: OSI Approved :: MIT License
Classifier: Operating System :: OS Independent
Classifier: Topic :: Security
Classifier: Topic :: Software Development :: Code Generators
Classifier: Topic :: Software Development :: Interpreters
Requires-Python: >=3.6
